odoo/addons/stock_account_prepare_anglo_saxon_out_lines_hook/README.rst
odoo/addons/stock_account_prepare_anglo_saxon_out_lines_hook/__init__.py
odoo/addons/stock_account_prepare_anglo_saxon_out_lines_hook/__manifest__.py
odoo/addons/stock_account_prepare_anglo_saxon_out_lines_hook/hooks.py
odoo/addons/stock_account_prepare_anglo_saxon_out_lines_hook/i18n/sl.po
odoo/addons/stock_account_prepare_anglo_saxon_out_lines_hook/i18n/stock_account_prepare_anglo_saxon_out_lines_hook.pot
odoo/addons/stock_account_prepare_anglo_saxon_out_lines_hook/models/__init__.py
odoo/addons/stock_account_prepare_anglo_saxon_out_lines_hook/models/account_move.py
odoo/addons/stock_account_prepare_anglo_saxon_out_lines_hook/models/account_move_line.py
odoo/addons/stock_account_prepare_anglo_saxon_out_lines_hook/static/description/icon.png
odoo14_addon_stock_account_prepare_anglo_saxon_out_lines_hook-14.0.1.0.5.dist-info/METADATA
odoo14_addon_stock_account_prepare_anglo_saxon_out_lines_hook-14.0.1.0.5.dist-info/WHEEL
odoo14_addon_stock_account_prepare_anglo_saxon_out_lines_hook-14.0.1.0.5.dist-info/top_level.txt
odoo14_addon_stock_account_prepare_anglo_saxon_out_lines_hook-14.0.1.0.5.dist-info/RECORD
